heprops/__init__.py
heprops/helium.py
heprops/potential.py
heprops-1.3.0.dist-info/LICENSE
heprops-1.3.0.dist-info/METADATA
heprops-1.3.0.dist-info/WHEEL
heprops-1.3.0.dist-info/top_level.txt
heprops-1.3.0.dist-info/RECORD
