Metadata-Version: 2.1
Name: heprops
Version: 1.3.0
Summary: Properties of the chemical element helium.
Home-page: https://github.com/agdelma/heprops
Author: Adrian Del Maestro
Author-email: adrian@delmaestro.org
License: MIT
Classifier: License :: OSI Approved :: MIT License
Classifier: Programming Language :: Python :: 3.6
Classifier: Programming Language :: Python :: 3.7
Classifier: Programming Language :: Python :: 3.9
Classifier: Topic :: Scientific/Engineering :: Physics
Requires-Python: >=3.6
License-File: LICENSE
Requires-Dist: numpy
Requires-Dist: scipy
